CHANGES.txt
README.txt
bootstrap.py
buildout.cfg
setup.py
src/zope/__init__.py
src/zope.app.workflow.egg-info/PKG-INFO
src/zope.app.workflow.egg-info/SOURCES.txt
src/zope.app.workflow.egg-info/dependency_links.txt
src/zope.app.workflow.egg-info/namespace_packages.txt
src/zope.app.workflow.egg-info/not-zip-safe
src/zope.app.workflow.egg-info/requires.txt
src/zope.app.workflow.egg-info/top_level.txt
src/zope/app/__init__.py
src/zope/app/workflow/SETUP.cfg
src/zope/app/workflow/__init__.py
src/zope/app/workflow/configure.zcml
src/zope/app/workflow/definition.py
src/zope/app/workflow/ftesting.zcml
src/zope/app/workflow/instance.py
src/zope/app/workflow/testing.py
src/zope/app/workflow/workflow-configure.zcml
src/zope/app/workflow/browser/__init__.py
src/zope/app/workflow/browser/configure.zcml
src/zope/app/workflow/browser/definition.py
src/zope/app/workflow/browser/definition_index.pt
src/zope/app/workflow/browser/importexport_index.pt
src/zope/app/workflow/browser/instance.py
src/zope/app/workflow/browser/instance_index.pt
src/zope/app/workflow/browser/instancecontainer_index.pt
src/zope/app/workflow/browser/instancecontainer_main.pt
src/zope/app/workflow/interfaces/__init__.py
src/zope/app/workflow/interfaces/wfmc.py
src/zope/app/workflow/stateful/__init__.py
src/zope/app/workflow/stateful/configure.zcml
src/zope/app/workflow/stateful/contentworkflow.py
src/zope/app/workflow/stateful/definition.py
src/zope/app/workflow/stateful/instance.py
src/zope/app/workflow/stateful/interfaces.py
src/zope/app/workflow/stateful/testobject.py
src/zope/app/workflow/stateful/testobject.zcml
src/zope/app/workflow/stateful/xmlexport_template.pt
src/zope/app/workflow/stateful/xmlimportexport.py
src/zope/app/workflow/stateful/browser/__init__.py
src/zope/app/workflow/stateful/browser/add.pt
src/zope/app/workflow/stateful/browser/addstate.pt
src/zope/app/workflow/stateful/browser/addtransition.pt
src/zope/app/workflow/stateful/browser/configure.zcml
src/zope/app/workflow/stateful/browser/content_filter.py
src/zope/app/workflow/stateful/browser/contentworkflow.py
src/zope/app/workflow/stateful/browser/contentworkflow_registry.pt
src/zope/app/workflow/stateful/browser/definition.py
src/zope/app/workflow/stateful/browser/definition_edit.pt
src/zope/app/workflow/stateful/browser/definition_index.pt
